setup.py
distributions_gaussian_binomial_exercise/Binomialdistribution.py
distributions_gaussian_binomial_exercise/Gaussiandistribution.py
distributions_gaussian_binomial_exercise/Generaldistribution.py
distributions_gaussian_binomial_exercise/__init__.py
distributions_gaussian_binomial_exercise.egg-info/PKG-INFO
distributions_gaussian_binomial_exercise.egg-info/SOURCES.txt
distributions_gaussian_binomial_exercise.egg-info/dependency_links.txt
distributions_gaussian_binomial_exercise.egg-info/not-zip-safe
distributions_gaussian_binomial_exercise.egg-info/top_level.txt