Metadata-Version: 1.0
Name: distributions-gaussian-binomial-exercise
Version: 1.0
Summary: Gaussian distributions and Binomial distributions
Home-page: UNKNOWN
Author: JL
Author-email: UNKNOWN
License: UNKNOWN
Platform: UNKNOWN
